<Properties StartupConfiguration="{C7C9A02D-1BDE-3FCB-81C5-ED3D46864C6B}|">
  <MonoDevelop.Ide.Workbench ActiveDocument="Assets/scripts/GameStart.cs">
    <Files>
      <File FileName="Assets/scripts/SceneMove.cs" Line="17" Column="5" />
      <File FileName="Assets/scripts/Flash.cs" Line="29" Column="1" />
      <File FileName="Assets/scripts/GameStart.cs" Line="33" Column="1" />
    </Files>
  </MonoDevelop.Ide.Workbench>
  <MonoDevelop.Ide.DebuggingService.PinnedWatches />
  <MonoDevelop.Ide.Workspace ActiveConfiguration="Debug" />
  <MonoDevelop.Ide.ItemProperties.Assembly-CSharp PreferredExecutionTarget="Unity.Editor" />
  <MonoDevelop.Ide.DebuggingService.Breakpoints>
    <BreakpointStore />
  </MonoDevelop.Ide.DebuggingService.Breakpoints>
  <MultiItemStartupConfigurations />
</Properties>